<?xml version="1.0" encoding="utf-8" ?>
<dwsync>
<file name="header_bg.png" server="54.217.240.96//data/disk/o2/distro/001/ubercart-2.11.1-6.28.1/sites/rent.drupalflex.com/themes/rentit_ar/" local="130114589100000000" remote="130114589100000000" Dst="0" />
<file name="search_bg.png" server="54.217.240.96//data/disk/o2/distro/001/ubercart-2.11.1-6.28.1/sites/rent.drupalflex.com/themes/rentit_ar/" local="130114589100000000" remote="130114589100000000" Dst="0" />
<file name="spectacular-themes-bg.png" server="54.217.240.96//data/disk/o2/distro/001/ubercart-2.11.1-6.28.1/sites/rent.drupalflex.com/themes/rentit_ar/" local="130114589100000000" remote="130114589100000000" Dst="0" />
<file name="node-bullets.png" server="54.217.240.96//data/disk/o2/distro/001/ubercart-2.11.1-6.28.1/sites/rent.drupalflex.com/themes/rentit_ar/" local="130114589100000000" remote="130114589100000000" Dst="0" />
<file name="free-web-setup-bg.jpg" server="54.217.240.96//data/disk/o2/distro/001/ubercart-2.11.1-6.28.1/sites/rent.drupalflex.com/themes/rentit_ar/" local="130114589100000000" remote="130114589100000000" Dst="0" />
<file name="multimedia-bg.png" server="54.217.240.96//data/disk/o2/distro/001/ubercart-2.11.1-6.28.1/sites/rent.drupalflex.com/themes/rentit_ar/" local="130114589100000000" remote="130114589100000000" Dst="0" />
<file name="custom-social-media-buttons.png" server="54.217.240.96//data/disk/o2/distro/001/ubercart-2.11.1-6.28.1/sites/rent.drupalflex.com/themes/rentit_ar/" local="130114589100000000" remote="130114589100000000" Dst="0" />
<file name="monthly-updates.png" server="54.217.240.96//data/disk/o2/distro/001/ubercart-2.11.1-6.28.1/sites/rent.drupalflex.com/themes/rentit_ar/" local="130114589100000000" remote="130114589100000000" Dst="0" />
<file name="web-optimization.jpg" server="54.217.240.96//data/disk/o2/distro/001/ubercart-2.11.1-6.28.1/sites/rent.drupalflex.com/themes/rentit_ar/" local="130114589100000000" remote="130114589100000000" Dst="0" />
<file name="title-bg.gif" server="54.217.240.96//data/disk/o2/distro/001/ubercart-2.11.1-6.28.1/sites/rent.drupalflex.com/themes/rentit_ar/" local="130114589100000000" remote="130114589100000000" Dst="0" />
<file name="tab-content-bg.png" server="54.217.240.96//data/disk/o2/distro/001/ubercart-2.11.1-6.28.1/sites/rent.drupalflex.com/themes/rentit_ar/" local="130114589100000000" remote="130114589100000000" Dst="0" />
<file name="orange-arrows.png" server="54.217.240.96//data/disk/o2/distro/001/ubercart-2.11.1-6.28.1/sites/rent.drupalflex.com/themes/rentit_ar/" local="130114589100000000" remote="130114589100000000" Dst="0" />
<file name="grid-price-bg.png" server="54.217.240.96//data/disk/o2/distro/001/ubercart-2.11.1-6.28.1/sites/rent.drupalflex.com/themes/rentit_ar/" local="130114589100000000" remote="130114589100000000" Dst="0" />
<file name="black-tab.png" server="54.217.240.96//data/disk/o2/distro/001/ubercart-2.11.1-6.28.1/sites/rent.drupalflex.com/themes/rentit_ar/" local="130114589100000000" remote="130114589100000000" Dst="0" />
<file name="blue-tab.png" server="54.217.240.96//data/disk/o2/distro/001/ubercart-2.11.1-6.28.1/sites/rent.drupalflex.com/themes/rentit_ar/" local="130114589100000000" remote="130114589100000000" Dst="0" />
<file name="purple-tab.png" server="54.217.240.96//data/disk/o2/distro/001/ubercart-2.11.1-6.28.1/sites/rent.drupalflex.com/themes/rentit_ar/" local="130114589100000000" remote="130114589100000000" Dst="0" />
<file name="deep-purple-tab.png" server="54.217.240.96//data/disk/o2/distro/001/ubercart-2.11.1-6.28.1/sites/rent.drupalflex.com/themes/rentit_ar/" local="130114589100000000" remote="130114589100000000" Dst="0" />
<file name="green-tab.png" server="54.217.240.96//data/disk/o2/distro/001/ubercart-2.11.1-6.28.1/sites/rent.drupalflex.com/themes/rentit_ar/" local="130114589100000000" remote="130114589100000000" Dst="0" />
<file name="not-sure.png" server="54.217.240.96//data/disk/o2/distro/001/ubercart-2.11.1-6.28.1/sites/rent.drupalflex.com/themes/rentit_ar/" local="130114589100000000" remote="130114589100000000" Dst="0" />
<file name="start-your-plan-refined.png" server="54.217.240.96//data/disk/o2/distro/001/ubercart-2.11.1-6.28.1/sites/rent.drupalflex.com/themes/rentit_ar/" local="130114589100000000" remote="130114589100000000" Dst="0" />
<file name="payment-options-bg.png" server="54.217.240.96//data/disk/o2/distro/001/ubercart-2.11.1-6.28.1/sites/rent.drupalflex.com/themes/rentit_ar/" local="130114589100000000" remote="130114589100000000" Dst="0" />
<file name="footer-logo-2.png" server="54.217.240.96//data/disk/o2/distro/001/ubercart-2.11.1-6.28.1/sites/rent.drupalflex.com/themes/rentit_ar/" local="130114589100000000" remote="130114589100000000" Dst="0" />
<file name="footer-bg.png" server="54.217.240.96//data/disk/o2/distro/001/ubercart-2.11.1-6.28.1/sites/rent.drupalflex.com/themes/rentit_ar/" local="130114589100000000" remote="130114589100000000" Dst="0" />
<file name="features-nav-bg.jpg" server="54.217.240.96//data/disk/o2/distro/001/ubercart-2.11.1-6.28.1/sites/rent.drupalflex.com/themes/rentit_ar/" local="130114589100000000" remote="130114589100000000" Dst="0" />
<file name="downward-menu-arrow.png" server="54.217.240.96//data/disk/o2/distro/001/ubercart-2.11.1-6.28.1/sites/rent.drupalflex.com/themes/rentit_ar/" local="130114589100000000" remote="130114589100000000" Dst="0" />
<file name="eol-icon.png" server="54.217.240.96//data/disk/o2/distro/001/ubercart-2.11.1-6.28.1/sites/rent.drupalflex.com/themes/rentit_ar/" local="130114589100000000" remote="130114589100000000" Dst="0" />
<file name="qol-icon.png" server="54.217.240.96//data/disk/o2/distro/001/ubercart-2.11.1-6.28.1/sites/rent.drupalflex.com/themes/rentit_ar/" local="130114589100000000" remote="130114589100000000" Dst="0" />
<file name="pol-icon.png" server="54.217.240.96//data/disk/o2/distro/001/ubercart-2.11.1-6.28.1/sites/rent.drupalflex.com/themes/rentit_ar/" local="130114589100000000" remote="130114589100000000" Dst="0" />
<file name="bol-icon.png" server="54.217.240.96//data/disk/o2/distro/001/ubercart-2.11.1-6.28.1/sites/rent.drupalflex.com/themes/rentit_ar/" local="130114589100000000" remote="130114589100000000" Dst="0" />
<file name="sol-icon.png" server="54.217.240.96//data/disk/o2/distro/001/ubercart-2.11.1-6.28.1/sites/rent.drupalflex.com/themes/rentit_ar/" local="130114589100000000" remote="130114589100000000" Dst="0" />
<file name="wrapper-bg.png" server="54.217.240.96//data/disk/o2/distro/001/ubercart-2.11.1-6.28.1/sites/rent.drupalflex.com/themes/rentit_ar/" local="130114589100000000" remote="130114589100000000" Dst="0" />
<file name="social-media-icons.png" server="54.217.240.96//data/disk/o2/distro/001/ubercart-2.11.1-6.28.1/sites/rent.drupalflex.com/themes/rentit_ar/" local="130118035549050389" remote="130118066380000000" Dst="0" />
<file name="login-text.png" server="54.217.240.96:2412//data/disk/o2/distro/001/ubercart-2.11.1-6.28.1/sites/rent.drupalflex.com/themes/rentit_ar/" local="130130352512225052" remote="130130385640000000" Dst="0" />
<file name="modal-login-speech-bubble.png" server="54.217.240.96:2412//data/disk/o2/distro/001/ubercart-2.11.1-6.28.1/sites/rent.drupalflex.com/themes/rentit_ar/" local="130130342267499087" remote="130130385660000000" Dst="0" />
<file name="modal-form-arrow.png" server="54.217.240.96:2412//data/disk/o2/distro/001/ubercart-2.11.1-6.28.1/sites/rent.drupalflex.com/themes/rentit_ar/" local="130130341111432964" remote="130130385680000000" Dst="0" />
<file name="modal-login-button.png" server="54.217.240.96:2412//data/disk/o2/distro/001/ubercart-2.11.1-6.28.1/sites/rent.drupalflex.com/themes/rentit_ar/" local="130130340569651976" remote="130130385700000000" Dst="0" />
<file name="modal-login-title.png" server="54.217.240.96:2412//data/disk/o2/distro/001/ubercart-2.11.1-6.28.1/sites/rent.drupalflex.com/themes/rentit_ar/" local="130130340069193351" remote="130130385720000000" Dst="0" />
<file name="bottom-buy-banner.png" server="54.217.240.96:2412//data/disk/o2/distro/001/ubercart-2.11.1-6.28.1/sites/a.b.drupalflex.com/themes/rentit_ar/" local="130136661125578884" remote="130136661270000000" Dst="0" />
<file name="domain-choice-span.png" server="54.217.240.96:2412//data/disk/o2/distro/001/ubercart-2.11.1-6.28.1/sites/a.b.drupalflex.com/themes/rentit_ar/" local="130136678447339632" remote="130136685810000000" Dst="0" />
</dwsync>